{
"meta":{"test_sets":[],"test_metrics":[],"learn_metrics":[{"best_value":"Min","name":"Logloss"}],"launch_mode":"Train","parameters":"","iteration_count":500,"learn_sets":["learn"],"name":"experiment"},
"iterations":[
{"learn":[0.6668579102],"iteration":0,"passed_time":0.002248290238,"remaining_time":1.121896829},
{"learn":[0.6396682739],"iteration":1,"passed_time":0.003996323941,"remaining_time":0.9950846613},
{"learn":[0.616975708],"iteration":2,"passed_time":0.005710656345,"remaining_time":0.9460654011},
{"learn":[0.5962851969],"iteration":3,"passed_time":0.007300362956,"remaining_time":0.9052450066},
{"learn":[0.5830174764],"iteration":4,"passed_time":0.008348102377,"remaining_time":0.8264621353},
{"learn":[0.5662731934],"iteration":5,"passed_time":0.009929930651,"remaining_time":0.8175642903},
{"learn":[0.5522440592],"iteration":6,"passed_time":0.01155197682,"remaining_time":0.8135892247},
{"learn":[0.5394410706],"iteration":7,"passed_time":0.01313333328,"remaining_time":0.8076999969},
{"learn":[0.5270620219],"iteration":8,"passed_time":0.01474022275,"remaining_time":0.8041610409},
{"learn":[0.5168957011],"iteration":9,"passed_time":0.0163804405,"remaining_time":0.8026415844},
{"learn":[0.5094477844],"iteration":10,"passed_time":0.01801819466,"remaining_time":0.8009906535},
{"learn":[0.5032519531],"iteration":11,"passed_time":0.01961792747,"remaining_time":0.7977957169},
{"learn":[0.4955742391],"iteration":12,"passed_time":0.021650855,"remaining_time":0.8110743372},
{"learn":[0.4868835449],"iteration":13,"passed_time":0.02329149946,"remaining_time":0.8085477669},
{"learn":[0.4818464152],"iteration":14,"passed_time":0.02517639601,"remaining_time":0.8140368042},
{"learn":[0.4753716532],"iteration":15,"passed_time":0.02686616767,"remaining_time":0.8127015721},
{"learn":[0.4694517008],"iteration":16,"passed_time":0.02867914826,"remaining_time":0.8148252123},
{"learn":[0.4641959635],"iteration":17,"passed_time":0.0302996759,"remaining_time":0.8113579879},
{"learn":[0.4597502645],"iteration":18,"passed_time":0.03186989143,"remaining_time":0.8068114619},
{"learn":[0.4552454631],"iteration":19,"passed_time":0.03347345744,"remaining_time":0.8033629785},
{"learn":[0.4511737569],"iteration":20,"passed_time":0.03510962648,"remaining_time":0.8008338612},
{"learn":[0.4473016357],"iteration":21,"passed_time":0.03671335573,"remaining_time":0.7976810927},
{"learn":[0.4443262227],"iteration":22,"passed_time":0.03831019967,"remaining_time":0.794520228},
{"learn":[0.4424000041],"iteration":23,"passed_time":0.03995621091,"remaining_time":0.7924648497},
{"learn":[0.4394590251],"iteration":24,"passed_time":0.04156391799,"remaining_time":0.7897144418},
{"learn":[0.4378755697],"iteration":25,"passed_time":0.04323717693,"remaining_time":0.7882469949},
{"learn":[0.4363095093],"iteration":26,"passed_time":0.04487294289,"remaining_time":0.7861074811},
{"learn":[0.4341203308],"iteration":27,"passed_time":0.04647973785,"remaining_time":0.7835155809},
{"learn":[0.4322434489],"iteration":28,"passed_time":0.0482747731,"remaining_time":0.784048901},
{"learn":[0.4307817586],"iteration":29,"passed_time":0.04990518445,"remaining_time":0.7818478898},
{"learn":[0.4296796163],"iteration":30,"passed_time":0.05154518456,"remaining_time":0.7798287599},
{"learn":[0.4278441874],"iteration":31,"passed_time":0.05320741068,"remaining_time":0.7781583812},
{"learn":[0.4255577596],"iteration":32,"passed_time":0.05482357172,"remaining_time":0.7758366059},
{"learn":[0.4246892548],"iteration":33,"passed_time":0.05655463593,"remaining_time":0.7751311865},
{"learn":[0.423164978],"iteration":34,"passed_time":0.05869531927,"remaining_time":0.7798092418},
{"learn":[0.4211483002],"iteration":35,"passed_time":0.06034819721,"remaining_time":0.7778212084},
{"learn":[0.4202114105],"iteration":36,"passed_time":0.06209021763,"remaining_time":0.7769667773},
{"learn":[0.4186069743],"iteration":37,"passed_time":0.06375380191,"remaining_time":0.7751120127},
{"learn":[0.416755956],"iteration":38,"passed_time":0.06533440662,"remaining_time":0.7722861911},
{"learn":[0.4158534241],"iteration":39,"passed_time":0.06697698702,"remaining_time":0.7702353507},
{"learn":[0.4148045858],"iteration":40,"passed_time":0.06858832254,"remaining_time":0.7678546353},
{"learn":[0.4127063751],"iteration":41,"passed_time":0.07020323139,"remaining_time":0.7655495232},
{"learn":[0.4117170715],"iteration":42,"passed_time":0.07180267924,"remaining_time":0.7631121957},
{"learn":[0.4104765574],"iteration":43,"passed_time":0.07344036324,"remaining_time":0.761109219},
{"learn":[0.4098865255],"iteration":44,"passed_time":0.0755233795,"remaining_time":0.7636252816},
{"learn":[0.4089328003],"iteration":45,"passed_time":0.07801746041,"remaining_time":0.7699984136},
{"learn":[0.4076596069],"iteration":46,"passed_time":0.08051185562,"remaining_time":0.7759972467},
{"learn":[0.4063628642],"iteration":47,"passed_time":0.08342951602,"remaining_time":0.7856279425},
{"learn":[0.4052023824],"iteration":48,"passed_time":0.08522101232,"remaining_time":0.7843811542},
{"learn":[0.4043311564],"iteration":49,"passed_time":0.08685257278,"remaining_time":0.781673155},
{"learn":[0.4039288839],"iteration":50,"passed_time":0.08813694799,"remaining_time":0.7759507774},
{"learn":[0.4030516307],"iteration":51,"passed_time":0.08998266405,"remaining_time":0.7752352595},
{"learn":[0.4025919596],"iteration":52,"passed_time":0.09160624594,"remaining_time":0.7726036214},
{"learn":[0.4018914795],"iteration":53,"passed_time":0.0932544437,"remaining_time":0.7702126276},
{"learn":[0.4014232127],"iteration":54,"passed_time":0.09494533082,"remaining_time":0.7681940402},
{"learn":[0.4006840007],"iteration":55,"passed_time":0.09658874601,"remaining_time":0.7658107719},
{"learn":[0.3991678874],"iteration":56,"passed_time":0.09821254913,"remaining_time":0.7633010397},
{"learn":[0.3980540466],"iteration":57,"passed_time":0.0998698853,"remaining_time":0.7610774017},
{"learn":[0.3975784047],"iteration":58,"passed_time":0.1015495341,"remaining_time":0.759039738},
{"learn":[0.396960144],"iteration":59,"passed_time":0.1031680735,"remaining_time":0.7565658727},
{"learn":[0.3963506063],"iteration":60,"passed_time":0.1048171362,"remaining_time":0.7543397177},
{"learn":[0.3953177897],"iteration":61,"passed_time":0.1064880554,"remaining_time":0.7522865848},
{"learn":[0.3943033854],"iteration":62,"passed_time":0.1083757513,"remaining_time":0.7517492591},
{"learn":[0.3933597819],"iteration":63,"passed_time":0.1100366937,"remaining_time":0.749624976},
{"learn":[0.3928134918],"iteration":64,"passed_time":0.1116961291,"remaining_time":0.7475048638},
{"learn":[0.3927687836],"iteration":65,"passed_time":0.1125348871,"remaining_time":0.7400021362},
{"learn":[0.3918042501],"iteration":66,"passed_time":0.1144331268,"remaining_time":0.7395454315},
{"learn":[0.3910408529],"iteration":67,"passed_time":0.1164337119,"remaining_time":0.7396965228},
{"learn":[0.3903010559],"iteration":68,"passed_time":0.1186946946,"remaining_time":0.7414117878},
{"learn":[0.3897952779],"iteration":69,"passed_time":0.1207579863,"remaining_time":0.741799059},
{"learn":[0.3888720194],"iteration":70,"passed_time":0.1233417524,"remaining_time":0.7452621379},
{"learn":[0.3877401733],"iteration":71,"passed_time":0.1252813134,"remaining_time":0.7447278072},
{"learn":[0.3867945353],"iteration":72,"passed_time":0.1273513279,"remaining_time":0.7449180415},
{"learn":[0.3858412425],"iteration":73,"passed_time":0.1294632271,"remaining_time":0.7452883076},
{"learn":[0.3853065745],"iteration":74,"passed_time":0.1316931625,"remaining_time":0.7462612542},
{"learn":[0.3846590678],"iteration":75,"passed_time":0.1334035285,"remaining_time":0.7442512645},
{"learn":[0.3840694682],"iteration":76,"passed_time":0.1350726321,"remaining_time":0.7420223815},
{"learn":[0.3832923889],"iteration":77,"passed_time":0.1367331886,"remaining_time":0.7397616102},
{"learn":[0.3825343577],"iteration":78,"passed_time":0.1384204616,"remaining_time":0.7376584093},
{"learn":[0.3816887919],"iteration":79,"passed_time":0.1401064674,"remaining_time":0.7355589537},
{"learn":[0.381014684],"iteration":80,"passed_time":0.1418001488,"remaining_time":0.7335094119},
{"learn":[0.3803524272],"iteration":81,"passed_time":0.1434514295,"remaining_time":0.7312524089},
{"learn":[0.3799500529],"iteration":82,"passed_time":0.1451363864,"remaining_time":0.7291791942},
{"learn":[0.3795376078],"iteration":83,"passed_time":0.1467339742,"remaining_time":0.7266825388},
{"learn":[0.378739268],"iteration":84,"passed_time":0.1483689884,"remaining_time":0.7243897669},
{"learn":[0.37779363],"iteration":85,"passed_time":0.1503379721,"remaining_time":0.7237200052},
{"learn":[0.3773203532],"iteration":86,"passed_time":0.1520199635,"remaining_time":0.7216579877},
{"learn":[0.3765867106],"iteration":87,"passed_time":0.1536677396,"remaining_time":0.7194444171},
{"learn":[0.3759414927],"iteration":88,"passed_time":0.1553501398,"remaining_time":0.7174034545},
{"learn":[0.3752250671],"iteration":89,"passed_time":0.157030758,"remaining_time":0.715362342},
{"learn":[0.3748099264],"iteration":90,"passed_time":0.1586836639,"remaining_time":0.7132045991},
{"learn":[0.3740446472],"iteration":91,"passed_time":0.1604619967,"remaining_time":0.7116140722},
{"learn":[0.3735005188],"iteration":92,"passed_time":0.1621889613,"remaining_time":0.7097947017},
{"learn":[0.37287913],"iteration":93,"passed_time":0.1638678212,"remaining_time":0.7077695255},
{"learn":[0.37227211],"iteration":94,"passed_time":0.1654930075,"remaining_time":0.7055228214},
{"learn":[0.371812439],"iteration":95,"passed_time":0.1674812725,"remaining_time":0.7048170218},
{"learn":[0.3713500468],"iteration":96,"passed_time":0.1694037358,"remaining_time":0.7038113971},
{"learn":[0.3706554413],"iteration":97,"passed_time":0.1710788641,"remaining_time":0.7017724833},
{"learn":[0.3702700297],"iteration":98,"passed_time":0.1741669146,"remaining_time":0.7054639674},
{"learn":[0.3697100067],"iteration":99,"passed_time":0.1818023375,"remaining_time":0.7272093499},
{"learn":[0.3694656372],"iteration":100,"passed_time":0.1872631444,"remaining_time":0.739782125},
{"learn":[0.3687656148],"iteration":101,"passed_time":0.1904955267,"remaining_time":0.7433060746},
{"learn":[0.3681954447],"iteration":102,"passed_time":0.1952535929,"remaining_time":0.7525793823},
{"learn":[0.3676656087],"iteration":103,"passed_time":0.1984077523,"remaining_time":0.7554756724},
{"learn":[0.3671263631],"iteration":104,"passed_time":0.2029675944,"remaining_time":0.7635447597},
{"learn":[0.3664225769],"iteration":105,"passed_time":0.2074439392,"remaining_time":0.7710652078},
{"learn":[0.366005249],"iteration":106,"passed_time":0.2107304696,"remaining_time":0.7739913508},
{"learn":[0.3655595907],"iteration":107,"passed_time":0.2154842115,"remaining_time":0.7821278786},
{"learn":[0.3646942647],"iteration":108,"passed_time":0.2202173475,"remaining_time":0.7899539714},
{"learn":[0.3644275665],"iteration":109,"passed_time":0.224397697,"remaining_time":0.7955918347},
{"learn":[0.3637642924],"iteration":110,"passed_time":0.2290666257,"remaining_time":0.8027650217},
{"learn":[0.3629885356],"iteration":111,"passed_time":0.2332593225,"remaining_time":0.8080769385},
{"learn":[0.3622679647],"iteration":112,"passed_time":0.2370025222,"remaining_time":0.8116812045},
{"learn":[0.3617637634],"iteration":113,"passed_time":0.240270256,"remaining_time":0.8135466564},
{"learn":[0.3611403402],"iteration":114,"passed_time":0.2447567409,"remaining_time":0.819403002},
{"learn":[0.3604821777],"iteration":115,"passed_time":0.247716069,"remaining_time":0.8200256076},
{"learn":[0.360059967],"iteration":116,"passed_time":0.2524319477,"remaining_time":0.8263370597},
{"learn":[0.359797821],"iteration":117,"passed_time":0.2554788468,"remaining_time":0.8270586397},
{"learn":[0.3593836721],"iteration":118,"passed_time":0.260037156,"remaining_time":0.8325559363},
{"learn":[0.3589609782],"iteration":119,"passed_time":0.2636041241,"remaining_time":0.834746393},
{"learn":[0.3584613291],"iteration":120,"passed_time":0.2690188409,"remaining_time":0.842629262},
{"learn":[0.357852478],"iteration":121,"passed_time":0.2732088986,"remaining_time":0.8464997023},
{"learn":[0.3574183909],"iteration":122,"passed_time":0.2768396474,"remaining_time":0.8485247729},
{"learn":[0.3570639547],"iteration":123,"passed_time":0.280250858,"remaining_time":0.8497929243},
{"learn":[0.3564684041],"iteration":124,"passed_time":0.2844080127,"remaining_time":0.8532240381},
{"learn":[0.3561946615],"iteration":125,"passed_time":0.2874357243,"remaining_time":0.8531822292},
{"learn":[0.3555448151],"iteration":126,"passed_time":0.2915651008,"remaining_time":0.8563289967},
{"learn":[0.3551304626],"iteration":127,"passed_time":0.2932712942,"remaining_time":0.8523196988},
{"learn":[0.3546028646],"iteration":128,"passed_time":0.2949753448,"remaining_time":0.8483399452},
{"learn":[0.3539872742],"iteration":129,"passed_time":0.2966714512,"remaining_time":0.844372592},
{"learn":[0.3536009216],"iteration":130,"passed_time":0.2982881256,"remaining_time":0.8402161706},
{"learn":[0.3531356812],"iteration":131,"passed_time":0.3000122544,"remaining_time":0.8363978001},
{"learn":[0.3525652822],"iteration":132,"passed_time":0.3016833268,"remaining_time":0.8324645184},
{"learn":[0.3520961761],"iteration":133,"passed_time":0.3033834669,"remaining_time":0.8286443947},
{"learn":[0.3517171224],"iteration":134,"passed_time":0.3049974393,"remaining_time":0.8246227062},
{"learn":[0.3512621562],"iteration":135,"passed_time":0.3068780129,"remaining_time":0.8213499758},
{"learn":[0.3509592183],"iteration":136,"passed_time":0.3085078658,"remaining_time":0.8174332503},
{"learn":[0.3502805328],"iteration":137,"passed_time":0.3100857693,"remaining_time":0.8134133947},
{"learn":[0.349809316],"iteration":138,"passed_time":0.3117060434,"remaining_time":0.8095387171},
{"learn":[0.3495030721],"iteration":139,"passed_time":0.3133549264,"remaining_time":0.8057698107},
{"learn":[0.3491875966],"iteration":140,"passed_time":0.3150056099,"remaining_time":0.80203556},
{"learn":[0.3488838704],"iteration":141,"passed_time":0.3166127893,"remaining_time":0.7982209759},
{"learn":[0.3484601339],"iteration":142,"passed_time":0.3184491644,"remaining_time":0.7950094523},
{"learn":[0.3479899597],"iteration":143,"passed_time":0.3200739068,"remaining_time":0.7912938252},
{"learn":[0.347571106],"iteration":144,"passed_time":0.3216675433,"remaining_time":0.7875308818},
{"learn":[0.3469963582],"iteration":145,"passed_time":0.3232479425,"remaining_time":0.7837655593},
{"learn":[0.3464739482],"iteration":146,"passed_time":0.3248884366,"remaining_time":0.780174273},
{"learn":[0.3455488078],"iteration":147,"passed_time":0.3267078307,"remaining_time":0.7770348406},
{"learn":[0.344937795],"iteration":148,"passed_time":0.3284250706,"remaining_time":0.7736724818},
{"learn":[0.3439229329],"iteration":149,"passed_time":0.3300745535,"remaining_time":0.7701739582},
{"learn":[0.3433749135],"iteration":150,"passed_time":0.3317225751,"remaining_time":0.7666965478},
{"learn":[0.3426991526],"iteration":151,"passed_time":0.3335387689,"remaining_time":0.7636282341},
{"learn":[0.3418013509],"iteration":152,"passed_time":0.3353568728,"remaining_time":0.7605806201},
{"learn":[0.341633606],"iteration":153,"passed_time":0.3366469506,"remaining_time":0.7563626293},
{"learn":[0.3411317444],"iteration":154,"passed_time":0.3385324099,"remaining_time":0.753507622},
{"learn":[0.3404774475],"iteration":155,"passed_time":0.3409558958,"remaining_time":0.7518514625},
{"learn":[0.3398990885],"iteration":156,"passed_time":0.3428768677,"remaining_time":0.7490876792},
{"learn":[0.3393850454],"iteration":157,"passed_time":0.3445736199,"remaining_time":0.7458492279},
{"learn":[0.3389371236],"iteration":158,"passed_time":0.3463490266,"remaining_time":0.7427988559},
{"learn":[0.3385226695],"iteration":159,"passed_time":0.3480365502,"remaining_time":0.7395776692},
{"learn":[0.3376973216],"iteration":160,"passed_time":0.349697837,"remaining_time":0.7363202903},
{"learn":[0.3373890432],"iteration":161,"passed_time":0.3513173702,"remaining_time":0.7329955007},
{"learn":[0.3371128591],"iteration":162,"passed_time":0.3529730675,"remaining_time":0.7297664034},
{"learn":[0.3366676331],"iteration":163,"passed_time":0.3546506021,"remaining_time":0.7266012337},
{"learn":[0.3362798055],"iteration":164,"passed_time":0.3562881344,"remaining_time":0.7233728788},
{"learn":[0.3355959066],"iteration":165,"passed_time":0.3582237411,"remaining_time":0.7207634308},
{"learn":[0.3352573395],"iteration":166,"passed_time":0.3602475395,"remaining_time":0.7183379081},
{"learn":[0.3348842367],"iteration":167,"passed_time":0.3619684136,"remaining_time":0.7153185316},
{"learn":[0.3344440206],"iteration":168,"passed_time":0.3641650636,"remaining_time":0.7132463672},
{"learn":[0.3338557434],"iteration":169,"passed_time":0.3662264245,"remaining_time":0.7109101181},
{"learn":[0.333213323],"iteration":170,"passed_time":0.368279806,"remaining_time":0.7085617321},
{"learn":[0.3328951263],"iteration":171,"passed_time":0.370006553,"remaining_time":0.7055938919},
{"learn":[0.3325924174],"iteration":172,"passed_time":0.3715981634,"remaining_time":0.7023849678},
{"learn":[0.3320483907],"iteration":173,"passed_time":0.3734015402,"remaining_time":0.6995913914},
{"learn":[0.3317986043],"iteration":174,"passed_time":0.375050804,"remaining_time":0.6965229217},
{"learn":[0.3310273997],"iteration":175,"passed_time":0.3766625856,"remaining_time":0.693401578},
{"learn":[0.3307725779],"iteration":176,"passed_time":0.3783297396,"remaining_time":0.6903983383},
{"learn":[0.3304051971],"iteration":177,"passed_time":0.3799336034,"remaining_time":0.6872956197},
{"learn":[0.329841334],"iteration":178,"passed_time":0.3815444177,"remaining_time":0.6842221123},
{"learn":[0.3295718384],"iteration":179,"passed_time":0.3831909767,"remaining_time":0.681228403},
{"learn":[0.3290924581],"iteration":180,"passed_time":0.3847954663,"remaining_time":0.678175435},
{"learn":[0.3282889557],"iteration":181,"passed_time":0.3866088456,"remaining_time":0.6755033677},
{"learn":[0.3280467987],"iteration":182,"passed_time":0.3883007523,"remaining_time":0.6726302649},
{"learn":[0.3276014964],"iteration":183,"passed_time":0.3899079754,"remaining_time":0.6696245664},
{"learn":[0.3268884277],"iteration":184,"passed_time":0.3915540253,"remaining_time":0.6667000971},
{"learn":[0.3263993073],"iteration":185,"passed_time":0.3931512501,"remaining_time":0.6637069491},
{"learn":[0.3261632284],"iteration":186,"passed_time":0.3948077507,"remaining_time":0.6608279464},
{"learn":[0.3258143616],"iteration":187,"passed_time":0.396482491,"remaining_time":0.6579922191},
{"learn":[0.3254815674],"iteration":188,"passed_time":0.3985995042,"remaining_time":0.6558965387},
{"learn":[0.3245118205],"iteration":189,"passed_time":0.4003569334,"remaining_time":0.653213944},
{"learn":[0.3241360982],"iteration":190,"passed_time":0.4019554033,"remaining_time":0.6502838723},
{"learn":[0.3237557729],"iteration":191,"passed_time":0.4045595081,"remaining_time":0.6489808776},
{"learn":[0.3227859497],"iteration":192,"passed_time":0.4063310265,"remaining_time":0.6463400266},
{"learn":[0.3224093882],"iteration":193,"passed_time":0.4079578008,"remaining_time":0.6434798301},
{"learn":[0.3218264262],"iteration":194,"passed_time":0.4097726285,"remaining_time":0.640926419},
{"learn":[0.3216352336],"iteration":195,"passed_time":0.4120530085,"remaining_time":0.6391026254},
{"learn":[0.3213007609],"iteration":196,"passed_time":0.4139350477,"remaining_time":0.63666152},
{"learn":[0.3208422343],"iteration":197,"passed_time":0.4159325656,"remaining_time":0.6344021961},
{"learn":[0.3204449463],"iteration":198,"passed_time":0.4201766441,"remaining_time":0.6355435672},
{"learn":[0.3201926676],"iteration":199,"passed_time":0.4249465579,"remaining_time":0.6374198369},
{"learn":[0.3196957397],"iteration":200,"passed_time":0.4285751853,"remaining_time":0.6375322408},
{"learn":[0.3192240143],"iteration":201,"passed_time":0.4331262232,"remaining_time":0.6389683887},
{"learn":[0.3188011169],"iteration":202,"passed_time":0.4388511779,"remaining_time":0.6420630533},
{"learn":[0.3183220418],"iteration":203,"passed_time":0.4489194305,"remaining_time":0.6513732913},
{"learn":[0.3178482564],"iteration":204,"passed_time":0.4531324459,"remaining_time":0.6520686417},
{"learn":[0.3172277323],"iteration":205,"passed_time":0.4577137744,"remaining_time":0.6532419887},
{"learn":[0.3168164571],"iteration":206,"passed_time":0.4607925433,"remaining_time":0.6522329237},
{"learn":[0.3163105774],"iteration":207,"passed_time":0.4638559587,"remaining_time":0.6511824036},
{"learn":[0.3158561961],"iteration":208,"passed_time":0.4664750656,"remaining_time":0.6494939909},
{"learn":[0.3152085114],"iteration":209,"passed_time":0.468557953,"remaining_time":0.6470562208},
{"learn":[0.3148510742],"iteration":210,"passed_time":0.4718762753,"remaining_time":0.6463139505},
{"learn":[0.3145563253],"iteration":211,"passed_time":0.473570231,"remaining_time":0.6433406911},
{"learn":[0.3141046397],"iteration":212,"passed_time":0.4757466668,"remaining_time":0.6410295464},
{"learn":[0.3136535136],"iteration":213,"passed_time":0.4787817119,"remaining_time":0.6398671476},
{"learn":[0.31348025],"iteration":214,"passed_time":0.4864506391,"remaining_time":0.644829917},
{"learn":[0.3131050618],"iteration":215,"passed_time":0.4898313222,"remaining_time":0.6440374793},
{"learn":[0.3126329295],"iteration":216,"passed_time":0.4963802684,"remaining_time":0.6473530689},
{"learn":[0.3121843465],"iteration":217,"passed_time":0.4985436102,"remaining_time":0.644905037},
{"learn":[0.3118213399],"iteration":218,"passed_time":0.5005283505,"remaining_time":0.6422304406},
{"learn":[0.3112864685],"iteration":219,"passed_time":0.5059197896,"remaining_time":0.643897914},
{"learn":[0.3109243266],"iteration":220,"passed_time":0.5109128098,"remaining_time":0.6449985247},
{"learn":[0.3107563782],"iteration":221,"passed_time":0.5152420107,"remaining_time":0.6452129684},
{"learn":[0.3103181712],"iteration":222,"passed_time":0.5193050335,"remaining_time":0.6450560282},
{"learn":[0.3099836731],"iteration":223,"passed_time":0.5233015522,"remaining_time":0.6447822696},
{"learn":[0.3091530355],"iteration":224,"passed_time":0.5275100858,"remaining_time":0.6447345493},
{"learn":[0.3084527588],"iteration":225,"passed_time":0.5296910121,"remaining_time":0.642191758},
{"learn":[0.3080449168],"iteration":226,"passed_time":0.5321090001,"remaining_time":0.6399372557},
{"learn":[0.3077901204],"iteration":227,"passed_time":0.5339027503,"remaining_time":0.6369366143},
{"learn":[0.3072817993],"iteration":228,"passed_time":0.5362834337,"remaining_time":0.634641094},
{"learn":[0.307072525],"iteration":229,"passed_time":0.5383585429,"remaining_time":0.6319861156},
{"learn":[0.3067792257],"iteration":230,"passed_time":0.5417908326,"remaining_time":0.6309165973},
{"learn":[0.3064489237],"iteration":231,"passed_time":0.5449866032,"remaining_time":0.6295534899},
{"learn":[0.3059476217],"iteration":232,"passed_time":0.5488676875,"remaining_time":0.6289599681},
{"learn":[0.3056634521],"iteration":233,"passed_time":0.5528454547,"remaining_time":0.6284482519},
{"learn":[0.3052707418],"iteration":234,"passed_time":0.5556774328,"remaining_time":0.6266149774},
{"learn":[0.3049170431],"iteration":235,"passed_time":0.5574291823,"remaining_time":0.6235648479},
{"learn":[0.3044436646],"iteration":236,"passed_time":0.5592617649,"remaining_time":0.6206153762},
{"learn":[0.3038500214],"iteration":237,"passed_time":0.5632130361,"remaining_time":0.620007628},
{"learn":[0.3034181976],"iteration":238,"passed_time":0.5655079298,"remaining_time":0.6175630531},
{"learn":[0.3025452677],"iteration":239,"passed_time":0.5676071402,"remaining_time":0.6149077352},
{"learn":[0.3018689473],"iteration":240,"passed_time":0.5698555192,"remaining_time":0.6124173422},
{"learn":[0.3014550273],"iteration":241,"passed_time":0.5720571437,"remaining_time":0.6098791036},
{"learn":[0.3009580994],"iteration":242,"passed_time":0.5742632715,"remaining_time":0.6073483983},
{"learn":[0.3007247925],"iteration":243,"passed_time":0.5784680865,"remaining_time":0.6069173366},
{"learn":[0.3001640066],"iteration":244,"passed_time":0.5807281656,"remaining_time":0.604431356},
{"learn":[0.2998042806],"iteration":245,"passed_time":0.5831623707,"remaining_time":0.6021270006},
{"learn":[0.298986028],"iteration":246,"passed_time":0.59187096,"remaining_time":0.6062483922},
{"learn":[0.2986378988],"iteration":247,"passed_time":0.594569045,"remaining_time":0.6041588683},
{"learn":[0.2982400513],"iteration":248,"passed_time":0.5965725347,"remaining_time":0.601364282},
{"learn":[0.2978550212],"iteration":249,"passed_time":0.5983620958,"remaining_time":0.5983620958},
{"learn":[0.297535553],"iteration":250,"passed_time":0.6003179797,"remaining_time":0.5955345695},
{"learn":[0.2971271769],"iteration":251,"passed_time":0.6025526612,"remaining_time":0.5929883332},
{"learn":[0.29664505],"iteration":252,"passed_time":0.604808403,"remaining_time":0.5904651207},
{"learn":[0.2961956278],"iteration":253,"passed_time":0.6070016552,"remaining_time":0.5878834928},
{"learn":[0.2960122681],"iteration":254,"passed_time":0.6088134566,"remaining_time":0.5849384191},
{"learn":[0.2956156667],"iteration":255,"passed_time":0.6106420413,"remaining_time":0.5820181956},
{"learn":[0.2951135254],"iteration":256,"passed_time":0.6143681578,"remaining_time":0.5809006317},
{"learn":[0.2947216288],"iteration":257,"passed_time":0.616145552,"remaining_time":0.5779349751},
{"learn":[0.2942151642],"iteration":258,"passed_time":0.6266997678,"remaining_time":0.5831453438},
{"learn":[0.2939550018],"iteration":259,"passed_time":0.6357011515,"remaining_time":0.5868010629},
{"learn":[0.2934223938],"iteration":260,"passed_time":0.6453462656,"remaining_time":0.5909492624},
{"learn":[0.2930765788],"iteration":261,"passed_time":0.6513308603,"remaining_time":0.5916669647},
{"learn":[0.2927813466],"iteration":262,"passed_time":0.6629652353,"remaining_time":0.5974249459},
{"learn":[0.2922621918],"iteration":263,"passed_time":0.6696352311,"remaining_time":0.5986133126},
{"learn":[0.2919629924],"iteration":264,"passed_time":0.6781586565,"remaining_time":0.6013859784},
{"learn":[0.291507314],"iteration":265,"passed_time":0.6864141906,"remaining_time":0.6038380474},
{"learn":[0.2911043803],"iteration":266,"passed_time":0.6975678761,"remaining_time":0.6087390079},
{"learn":[0.2907570394],"iteration":267,"passed_time":0.703299575,"remaining_time":0.6088264977},
{"learn":[0.290516866],"iteration":268,"passed_time":0.7109953612,"remaining_time":0.6105573547},
{"learn":[0.2900345357],"iteration":269,"passed_time":0.7185941179,"remaining_time":0.6121357301},
{"learn":[0.2896165466],"iteration":270,"passed_time":0.7219715263,"remaining_time":0.6100792602},
{"learn":[0.289201889],"iteration":271,"passed_time":0.7270229138,"remaining_time":0.609416266},
{"learn":[0.2888632711],"iteration":272,"passed_time":0.7298165026,"remaining_time":0.6068437586},
{"learn":[0.2887081909],"iteration":273,"passed_time":0.7331060321,"remaining_time":0.604678698},
{"learn":[0.2883929443],"iteration":274,"passed_time":0.7386279126,"remaining_time":0.6043319285},
{"learn":[0.2879041545],"iteration":275,"passed_time":0.7433811842,"remaining_time":0.6033238596},
{"learn":[0.2875369517],"iteration":276,"passed_time":0.7482053357,"remaining_time":0.6023458117},
{"learn":[0.2871751658],"iteration":277,"passed_time":0.7562332535,"remaining_time":0.6038984974},
{"learn":[0.2868336487],"iteration":278,"passed_time":0.76150789,"remaining_time":0.6032015903},
{"learn":[0.2866019185],"iteration":279,"passed_time":0.7666657074,"remaining_time":0.6023801987},
{"learn":[0.2863473511],"iteration":280,"passed_time":0.7718874858,"remaining_time":0.6015777914},
{"learn":[0.2861275991],"iteration":281,"passed_time":0.7755334743,"remaining_time":0.5995258773},
{"learn":[0.2856255595],"iteration":282,"passed_time":0.7795885536,"remaining_time":0.5977763821},
{"learn":[0.285170695],"iteration":283,"passed_time":0.781981653,"remaining_time":0.5947466094},
{"learn":[0.2847961934],"iteration":284,"passed_time":0.7844391352,"remaining_time":0.5917698739},
{"learn":[0.2843378194],"iteration":285,"passed_time":0.7861652693,"remaining_time":0.5882495372},
{"learn":[0.2840391541],"iteration":286,"passed_time":0.7878627504,"remaining_time":0.5847204384},
{"learn":[0.2835619609],"iteration":287,"passed_time":0.7895163328,"remaining_time":0.581171745},
{"learn":[0.2833670807],"iteration":288,"passed_time":0.7928576536,"remaining_time":0.5788683907},
{"learn":[0.2831887309],"iteration":289,"passed_time":0.7957711751,"remaining_time":0.5762480923},
{"learn":[0.2828723145],"iteration":290,"passed_time":0.7980068674,"remaining_time":0.5731389529},
{"learn":[0.28219841],"iteration":291,"passed_time":0.799943493,"remaining_time":0.5698227621},
{"learn":[0.2819689433],"iteration":292,"passed_time":0.8021954818,"remaining_time":0.5667387875},
{"learn":[0.2813196309],"iteration":293,"passed_time":0.8041031893,"remaining_time":0.5634192415},
{"learn":[0.2808285014],"iteration":294,"passed_time":0.805804956,"remaining_time":0.5599661559},
{"learn":[0.2804252116],"iteration":295,"passed_time":0.8080955533,"remaining_time":0.5569307192},
{"learn":[0.2802420553],"iteration":296,"passed_time":0.8137596542,"remaining_time":0.5562060936},
{"learn":[0.2797592417],"iteration":297,"passed_time":0.8157963812,"remaining_time":0.5529894933},
{"learn":[0.2796022542],"iteration":298,"passed_time":0.8176992153,"remaining_time":0.5496907768},
{"learn":[0.2791370138],"iteration":299,"passed_time":0.8193980666,"remaining_time":0.5462653778},
{"learn":[0.2787358093],"iteration":300,"passed_time":0.8212826661,"remaining_time":0.5429742543},
{"learn":[0.2781580607],"iteration":301,"passed_time":0.8232507219,"remaining_time":0.539747162},
{"learn":[0.2779494476],"iteration":302,"passed_time":0.8250212293,"remaining_time":0.5363999412},
{"learn":[0.2775813293],"iteration":303,"passed_time":0.8270742751,"remaining_time":0.5332452563},
{"learn":[0.2772776794],"iteration":304,"passed_time":0.8288032602,"remaining_time":0.529890609},
{"learn":[0.2768659973],"iteration":305,"passed_time":0.8305491138,"remaining_time":0.5265572813},
{"learn":[0.2763000997],"iteration":306,"passed_time":0.8323198618,"remaining_time":0.5232499457},
{"learn":[0.2759260559],"iteration":307,"passed_time":0.8339609287,"remaining_time":0.5198717478},
{"learn":[0.2755999756],"iteration":308,"passed_time":0.8356268978,"remaining_time":0.516520186},
{"learn":[0.2752347565],"iteration":309,"passed_time":0.8392689436,"remaining_time":0.5143906428},
{"learn":[0.2749716441],"iteration":310,"passed_time":0.8416044797,"remaining_time":0.5114573848},
{"learn":[0.2746318054],"iteration":311,"passed_time":0.8437242243,"remaining_time":0.5083979301},
{"learn":[0.2742074839],"iteration":312,"passed_time":0.8475003393,"remaining_time":0.5063340685},
{"learn":[0.2737875366],"iteration":313,"passed_time":0.8500335885,"remaining_time":0.5035230811},
{"learn":[0.2734697469],"iteration":314,"passed_time":0.8544207679,"remaining_time":0.5018026732},
{"learn":[0.2730466715],"iteration":315,"passed_time":0.8621234709,"remaining_time":0.5019959451},
{"learn":[0.272694397],"iteration":316,"passed_time":0.8695561755,"remaining_time":0.5019835335},
{"learn":[0.2724420166],"iteration":317,"passed_time":0.8751849799,"remaining_time":0.5008920325},
{"learn":[0.2721760559],"iteration":318,"passed_time":0.8903717391,"remaining_time":0.5051952501},
{"learn":[0.2718093872],"iteration":319,"passed_time":0.8962823781,"remaining_time":0.5041588377},
{"learn":[0.2713713837],"iteration":320,"passed_time":0.9048490013,"remaining_time":0.5045731191},
{"learn":[0.2710714213],"iteration":321,"passed_time":0.9094754669,"remaining_time":0.502753519},
{"learn":[0.2707987722],"iteration":322,"passed_time":0.9139476549,"remaining_time":0.5008319966},
{"learn":[0.2705151367],"iteration":323,"passed_time":0.9192031876,"remaining_time":0.4993202501},
{"learn":[0.2703579966],"iteration":324,"passed_time":0.924285674,"remaining_time":0.497692286},
{"learn":[0.2699886068],"iteration":325,"passed_time":0.9292623233,"remaining_time":0.4959866388},
{"learn":[0.2696408335],"iteration":326,"passed_time":0.9371147383,"remaining_time":0.4957824151},
{"learn":[0.2693223063],"iteration":327,"passed_time":0.9469460931,"remaining_time":0.4965692927},
{"learn":[0.269214681],"iteration":328,"passed_time":0.9591785552,"remaining_time":0.4985396138},
{"learn":[0.2689034526],"iteration":329,"passed_time":0.9704558957,"remaining_time":0.499931825},
{"learn":[0.268575236],"iteration":330,"passed_time":0.9794196289,"remaining_time":0.5000662153},
{"learn":[0.2680507406],"iteration":331,"passed_time":0.987026463,"remaining_time":0.4994591741},
{"learn":[0.267752533],"iteration":332,"passed_time":0.9965821261,"remaining_time":0.4997874326},
{"learn":[0.2675395457],"iteration":333,"passed_time":1.019745199,"remaining_time":0.50681947},
{"learn":[0.2673552958],"iteration":334,"passed_time":1.023545149,"remaining_time":0.504134178},
{"learn":[0.266849645],"iteration":335,"passed_time":1.025455634,"remaining_time":0.5005200118},
{"learn":[0.2666932424],"iteration":336,"passed_time":1.027194197,"remaining_time":0.4968328015},
{"learn":[0.2664365387],"iteration":337,"passed_time":1.028940266,"remaining_time":0.4931607193},
{"learn":[0.2662480164],"iteration":338,"passed_time":1.030619369,"remaining_time":0.4894681961},
{"learn":[0.2659158834],"iteration":339,"passed_time":1.032266283,"remaining_time":0.4857723687},
{"learn":[0.2655834198],"iteration":340,"passed_time":1.033890224,"remaining_time":0.4820778464},
{"learn":[0.2650524394],"iteration":341,"passed_time":1.035519715,"remaining_time":0.4783979971},
{"learn":[0.2647336833],"iteration":342,"passed_time":1.042431366,"remaining_time":0.4771478849},
{"learn":[0.2646217855],"iteration":343,"passed_time":1.046894737,"remaining_time":0.4747545899},
{"learn":[0.264306132],"iteration":344,"passed_time":1.049991568,"remaining_time":0.4717353423},
{"learn":[0.2638832092],"iteration":345,"passed_time":1.05492334,"remaining_time":0.4695323538},
{"learn":[0.2635772705],"iteration":346,"passed_time":1.059719608,"remaining_time":0.4672538908},
{"learn":[0.2633429209],"iteration":347,"passed_time":1.064796752,"remaining_time":0.4650836387},
{"learn":[0.2629692841],"iteration":348,"passed_time":1.068984719,"remaining_time":0.462512013},
{"learn":[0.262420934],"iteration":349,"passed_time":1.074368978,"remaining_time":0.4604438478},
{"learn":[0.2621606445],"iteration":350,"passed_time":1.076150548,"remaining_time":0.4568274406},
{"learn":[0.2617893982],"iteration":351,"passed_time":1.078212789,"remaining_time":0.453339468},
{"learn":[0.2615990957],"iteration":352,"passed_time":1.080682819,"remaining_time":0.4500293894},
{"learn":[0.2614344788],"iteration":353,"passed_time":1.083281721,"remaining_time":0.4467772071},
{"learn":[0.2610197957],"iteration":354,"passed_time":1.08739893,"remaining_time":0.4441488585},
{"learn":[0.260919342],"iteration":355,"passed_time":1.094426319,"remaining_time":0.4426892977},
{"learn":[0.2606208801],"iteration":356,"passed_time":1.099065931,"remaining_time":0.4402420954},
{"learn":[0.2600901286],"iteration":357,"passed_time":1.104439095,"remaining_time":0.4380736075},
{"learn":[0.2599376678],"iteration":358,"passed_time":1.109105452,"remaining_time":0.4356096622},
{"learn":[0.2594289653],"iteration":359,"passed_time":1.114569155,"remaining_time":0.4334435602},
{"learn":[0.2591872152],"iteration":360,"passed_time":1.116723132,"remaining_time":0.4299848071},
{"learn":[0.258933665],"iteration":361,"passed_time":1.118792757,"remaining_time":0.4265011063},
{"learn":[0.2587164307],"iteration":362,"passed_time":1.120523452,"remaining_time":0.4228972808},
{"learn":[0.2584227498],"iteration":363,"passed_time":1.122540692,"remaining_time":0.4194108078},
{"learn":[0.2580995687],"iteration":364,"passed_time":1.124259338,"remaining_time":0.415821947},
{"learn":[0.2577570852],"iteration":365,"passed_time":1.12614501,"remaining_time":0.4123044573},
{"learn":[0.2575520833],"iteration":366,"passed_time":1.12807209,"remaining_time":0.4088108664},
{"learn":[0.2573004913],"iteration":367,"passed_time":1.130450467,"remaining_time":0.4054876676},
{"learn":[0.2569207255],"iteration":368,"passed_time":1.132129313,"remaining_time":0.4019212468},
{"learn":[0.2565750376],"iteration":369,"passed_time":1.134147817,"remaining_time":0.3984843683},
{"learn":[0.2563172404],"iteration":370,"passed_time":1.135861725,"remaining_time":0.394949225},
{"learn":[0.2559925334],"iteration":371,"passed_time":1.138037888,"remaining_time":0.3915829291},
{"learn":[0.2556061808],"iteration":372,"passed_time":1.139765838,"remaining_time":0.388070406},
{"learn":[0.255128123],"iteration":373,"passed_time":1.141595236,"remaining_time":0.3846016037},
{"learn":[0.2549099986],"iteration":374,"passed_time":1.143535303,"remaining_time":0.3811784342},
{"learn":[0.2546021525],"iteration":375,"passed_time":1.145209122,"remaining_time":0.3776753488},
{"learn":[0.2545054118],"iteration":376,"passed_time":1.147398089,"remaining_time":0.3743500395},
{"learn":[0.2542555745],"iteration":377,"passed_time":1.149200457,"remaining_time":0.3709059677},
{"learn":[0.2540607452],"iteration":378,"passed_time":1.151106096,"remaining_time":0.3675035295},
{"learn":[0.2536835225],"iteration":379,"passed_time":1.152787333,"remaining_time":0.3640381052},
{"learn":[0.2534519704],"iteration":380,"passed_time":1.154863956,"remaining_time":0.3607055401},
{"learn":[0.2530995178],"iteration":381,"passed_time":1.156841364,"remaining_time":0.3573489031},
{"learn":[0.2525787354],"iteration":382,"passed_time":1.158786563,"remaining_time":0.3539896288},
{"learn":[0.2523268636],"iteration":383,"passed_time":1.160504088,"remaining_time":0.3505689431},
{"learn":[0.2520616659],"iteration":384,"passed_time":1.162609681,"remaining_time":0.3472730215},
{"learn":[0.2519572194],"iteration":385,"passed_time":1.164275042,"remaining_time":0.3438532507},
{"learn":[0.2517001343],"iteration":386,"passed_time":1.166499921,"remaining_time":0.3406059202},
{"learn":[0.2513249715],"iteration":387,"passed_time":1.1681858,"remaining_time":0.3372082722},
{"learn":[0.2511441803],"iteration":388,"passed_time":1.170125502,"remaining_time":0.3338918528},
{"learn":[0.2508457184],"iteration":389,"passed_time":1.172095568,"remaining_time":0.3305910578},
{"learn":[0.2505418905],"iteration":390,"passed_time":1.173764847,"remaining_time":0.3272132181},
{"learn":[0.2502804565],"iteration":391,"passed_time":1.176204803,"remaining_time":0.3240564253},
{"learn":[0.2499069214],"iteration":392,"passed_time":1.177949939,"remaining_time":0.3207141054},
{"learn":[0.2496070099],"iteration":393,"passed_time":1.179848665,"remaining_time":0.3174212145},
{"learn":[0.2494166565],"iteration":394,"passed_time":1.181895318,"remaining_time":0.3141747049},
{"learn":[0.249139684],"iteration":395,"passed_time":1.184039436,"remaining_time":0.3109598519},
{"learn":[0.2486735026],"iteration":396,"passed_time":1.185887465,"remaining_time":0.3076735739},
{"learn":[0.2482511902],"iteration":397,"passed_time":1.187559992,"remaining_time":0.3043495457},
{"learn":[0.2480474091],"iteration":398,"passed_time":1.189319721,"remaining_time":0.3010558691},
{"learn":[0.2475294749],"iteration":399,"passed_time":1.191705199,"remaining_time":0.2979262997},
{"learn":[0.247212677],"iteration":400,"passed_time":1.193897915,"remaining_time":0.2947528519},
{"learn":[0.246909612],"iteration":401,"passed_time":1.197408658,"remaining_time":0.2919055932},
{"learn":[0.2466118876],"iteration":402,"passed_time":1.200006774,"remaining_time":0.2888353774},
{"learn":[0.2463194784],"iteration":403,"passed_time":1.201905519,"remaining_time":0.2856013116},
{"learn":[0.2459609985],"iteration":404,"passed_time":1.206032114,"remaining_time":0.2828964218},
{"learn":[0.2457730611],"iteration":405,"passed_time":1.208072311,"remaining_time":0.279701471},
{"learn":[0.2453573608],"iteration":406,"passed_time":1.209793267,"remaining_time":0.2764392477},
{"learn":[0.2451068115],"iteration":407,"passed_time":1.211488208,"remaining_time":0.2731787135},
{"learn":[0.2448604329],"iteration":408,"passed_time":1.213907017,"remaining_time":0.2700868913},
{"learn":[0.2447515869],"iteration":409,"passed_time":1.215612859,"remaining_time":0.2668418471},
{"learn":[0.2444526927],"iteration":410,"passed_time":1.217288809,"remaining_time":0.26359782},
{"learn":[0.2442804718],"iteration":411,"passed_time":1.219003561,"remaining_time":0.2603696926},
{"learn":[0.2441121419],"iteration":412,"passed_time":1.22065441,"remaining_time":0.2571354326},
{"learn":[0.243830363],"iteration":413,"passed_time":1.222362983,"remaining_time":0.2539208129},
{"learn":[0.2435248057],"iteration":414,"passed_time":1.224057148,"remaining_time":0.2507105002},
{"learn":[0.2432631429],"iteration":415,"passed_time":1.225746403,"remaining_time":0.2475064852},
{"learn":[0.2431706746],"iteration":416,"passed_time":1.227443373,"remaining_time":0.2443112709},
{"learn":[0.2428386943],"iteration":417,"passed_time":1.229124028,"remaining_time":0.2411200246},
{"learn":[0.2426933797],"iteration":418,"passed_time":1.234271034,"remaining_time":0.2386060948},
{"learn":[0.2423465474],"iteration":419,"passed_time":1.236192725,"remaining_time":0.2354652809},
{"learn":[0.2422098796],"iteration":420,"passed_time":1.237994528,"remaining_time":0.2323077619},
{"learn":[0.2418773397],"iteration":421,"passed_time":1.23967521,"remaining_time":0.2291342805},
{"learn":[0.2415966288],"iteration":422,"passed_time":1.241372354,"remaining_time":0.2259708541},
{"learn":[0.2413270569],"iteration":423,"passed_time":1.243064145,"remaining_time":0.2228133845},
{"learn":[0.2410530599],"iteration":424,"passed_time":1.244942876,"remaining_time":0.2196958016},
{"learn":[0.2408353678],"iteration":425,"passed_time":1.246627799,"remaining_time":0.2165503688},
{"learn":[0.2406287384],"iteration":426,"passed_time":1.248411637,"remaining_time":0.2134286873},
{"learn":[0.2400962575],"iteration":427,"passed_time":1.250158796,"remaining_time":0.2103070872},
{"learn":[0.2397639974],"iteration":428,"passed_time":1.252372595,"remaining_time":0.2072691242},
{"learn":[0.2395055644],"iteration":429,"passed_time":1.253992519,"remaining_time":0.2041383171},
{"learn":[0.2392059326],"iteration":430,"passed_time":1.255651137,"remaining_time":0.2010207157},
{"learn":[0.2389446004],"iteration":431,"passed_time":1.257270069,"remaining_time":0.197903622},
{"learn":[0.2387008921],"iteration":432,"passed_time":1.259531102,"remaining_time":0.1948928033},
{"learn":[0.2384115601],"iteration":433,"passed_time":1.26111523,"remaining_time":0.1917825004},
{"learn":[0.2383036296],"iteration":434,"passed_time":1.262776416,"remaining_time":0.1886907289},
{"learn":[0.2380159251],"iteration":435,"passed_time":1.264435808,"remaining_time":0.1856052562},
{"learn":[0.2379096476],"iteration":436,"passed_time":1.266115397,"remaining_time":0.1825292219},
{"learn":[0.2376498413],"iteration":437,"passed_time":1.267844981,"remaining_time":0.1794666411},
{"learn":[0.2373598989],"iteration":438,"passed_time":1.269615189,"remaining_time":0.176415778},
{"learn":[0.2369062805],"iteration":439,"passed_time":1.271292704,"remaining_time":0.1733580959},
{"learn":[0.2366773478],"iteration":440,"passed_time":1.272924641,"remaining_time":0.1703005755},
{"learn":[0.2365072378],"iteration":441,"passed_time":1.274886503,"remaining_time":0.1672927991},
{"learn":[0.2360735067],"iteration":442,"passed_time":1.276611491,"remaining_time":0.1642592664},
{"learn":[0.2358308411],"iteration":443,"passed_time":1.278273702,"remaining_time":0.1612237102},
{"learn":[0.2354993184],"iteration":444,"passed_time":1.2805462,"remaining_time":0.158269755},
{"learn":[0.2351967112],"iteration":445,"passed_time":1.289350884,"remaining_time":0.1561097483},
{"learn":[0.2347066498],"iteration":446,"passed_time":1.295878846,"remaining_time":0.1536500645},
{"learn":[0.2344159444],"iteration":447,"passed_time":1.299294245,"remaining_time":0.1508109392},
{"learn":[0.2341737366],"iteration":448,"passed_time":1.301498997,"remaining_time":0.1478317346},
{"learn":[0.2338384501],"iteration":449,"passed_time":1.303562424,"remaining_time":0.1448402693},
{"learn":[0.2333888753],"iteration":450,"passed_time":1.305822816,"remaining_time":0.1418743193},
{"learn":[0.2331256358],"iteration":451,"passed_time":1.308872601,"remaining_time":0.1389953204},
{"learn":[0.2330119832],"iteration":452,"passed_time":1.31129131,"remaining_time":0.1360500917},
{"learn":[0.2325524902],"iteration":453,"passed_time":1.31339775,"remaining_time":0.1330755429},
{"learn":[0.232074941],"iteration":454,"passed_time":1.316747981,"remaining_time":0.1302278223},
{"learn":[0.231890564],"iteration":455,"passed_time":1.318798998,"remaining_time":0.1272525349},
{"learn":[0.2316718038],"iteration":456,"passed_time":1.321152422,"remaining_time":0.1243097464},
{"learn":[0.2315407817],"iteration":457,"passed_time":1.323566375,"remaining_time":0.1213750824},
{"learn":[0.2314210765],"iteration":458,"passed_time":1.325785512,"remaining_time":0.1184252854},
{"learn":[0.2311448669],"iteration":459,"passed_time":1.327918905,"remaining_time":0.1154712092},
{"learn":[0.2310031382],"iteration":460,"passed_time":1.330016783,"remaining_time":0.1125176888},
{"learn":[0.2308259837],"iteration":461,"passed_time":1.331744627,"remaining_time":0.1095374368},
{"learn":[0.2304691569],"iteration":462,"passed_time":1.333419869,"remaining_time":0.1065583912},
{"learn":[0.230230662],"iteration":463,"passed_time":1.335062076,"remaining_time":0.1035824025},
{"learn":[0.2300112406],"iteration":464,"passed_time":1.336713667,"remaining_time":0.1006128566},
{"learn":[0.2295628357],"iteration":465,"passed_time":1.338352903,"remaining_time":0.09764806587},
{"learn":[0.2293534342],"iteration":466,"passed_time":1.340211417,"remaining_time":0.09470444705},
{"learn":[0.2287988281],"iteration":467,"passed_time":1.341969214,"remaining_time":0.09175857876},
{"learn":[0.228458252],"iteration":468,"passed_time":1.343610101,"remaining_time":0.08881004931},
{"learn":[0.2282658132],"iteration":469,"passed_time":1.345284085,"remaining_time":0.08586919692},
{"learn":[0.2279279073],"iteration":470,"passed_time":1.347267747,"remaining_time":0.08295279119},
{"learn":[0.2277005005],"iteration":471,"passed_time":1.348969832,"remaining_time":0.08002363409},
{"learn":[0.227406311],"iteration":472,"passed_time":1.350589789,"remaining_time":0.07709497738},
{"learn":[0.2272470856],"iteration":473,"passed_time":1.352380162,"remaining_time":0.07418119031},
{"learn":[0.2269628143],"iteration":474,"passed_time":1.354090534,"remaining_time":0.07126792286},
{"learn":[0.2266557821],"iteration":475,"passed_time":1.355732943,"remaining_time":0.06835628283},
{"learn":[0.2264413452],"iteration":476,"passed_time":1.357578159,"remaining_time":0.06545974353},
{"learn":[0.2262685394],"iteration":477,"passed_time":1.359238532,"remaining_time":0.0625590956},
{"learn":[0.2260273234],"iteration":478,"passed_time":1.360856386,"remaining_time":0.05966176223},
{"learn":[0.2258194987],"iteration":479,"passed_time":1.362972717,"remaining_time":0.05679052987},
{"learn":[0.2255986532],"iteration":480,"passed_time":1.364950974,"remaining_time":0.05391698233},
{"learn":[0.2253184001],"iteration":481,"passed_time":1.366903563,"remaining_time":0.05104619117},
{"learn":[0.2249608358],"iteration":482,"passed_time":1.368535165,"remaining_time":0.04816790435},
{"learn":[0.2246569316],"iteration":483,"passed_time":1.370297371,"remaining_time":0.04529908664},
{"learn":[0.2244302622],"iteration":484,"passed_time":1.371922693,"remaining_time":0.04243059876},
{"learn":[0.2241941325],"iteration":485,"passed_time":1.373535679,"remaining_time":0.03956687141},
{"learn":[0.2239496867],"iteration":486,"passed_time":1.37515642,"remaining_time":0.03670848759},
{"learn":[0.2237818654],"iteration":487,"passed_time":1.376907597,"remaining_time":0.03385838354},
{"learn":[0.2235642242],"iteration":488,"passed_time":1.378505055,"remaining_time":0.03100931616},
{"learn":[0.2232892863],"iteration":489,"passed_time":1.38013682,"remaining_time":0.02816605755},
{"learn":[0.223109258],"iteration":490,"passed_time":1.381805231,"remaining_time":0.02532840545},
{"learn":[0.2228185018],"iteration":491,"passed_time":1.38339297,"remaining_time":0.02249419463},
{"learn":[0.2226949056],"iteration":492,"passed_time":1.385099861,"remaining_time":0.0196667323},
{"learn":[0.222481308],"iteration":493,"passed_time":1.387059705,"remaining_time":0.01684687901},
{"learn":[0.222252477],"iteration":494,"passed_time":1.388841374,"remaining_time":0.01402870074},
{"learn":[0.221836853],"iteration":495,"passed_time":1.39081695,"remaining_time":0.01121626573},
{"learn":[0.2216549428],"iteration":496,"passed_time":1.392444459,"remaining_time":0.008405097336},
{"learn":[0.2213223521],"iteration":497,"passed_time":1.394125531,"remaining_time":0.005598897714},
{"learn":[0.2210212199],"iteration":498,"passed_time":1.395744582,"remaining_time":0.002797083331},
{"learn":[0.2207273102],"iteration":499,"passed_time":1.397374626,"remaining_time":0}
]}